{"lang":"en","favorite_count":53,"created_at":"2016-03-20T21:14:13.000Z","display_text_range":[0,140],"entities":{"hashtags":[],"urls":[],"user_mentions":[],"symbols":[]},"id_str":"711662152633995265","text":"How small is a microservice? Does it actually mean something or is it just a buzzword? Have we erlangers been doing microservices for 20 yrs","user":{"id_str":"15004019","name":"Robert Virding","profile_image_url_https":"https://pbs.twimg.com/profile_images/446056718519128064/P2MIAvat_normal.png","screen_name":"rvirding","verified":false},"conversation_count":16,"news_action_type":"conversation"}